{
  "info": {
    "_postman_id": "ac2a7da7-4c76-4952-8365-e50135f5b9f4",
    "name": "Task Manager API",
    "schema": "https://schema.getpostman.com/json/collection/v2.1.0/collection.json",
    "_exporter_id": "31705144"
  },
  "item": [
    {
      "name": "Login Request",
      "event": [
        {
          "listen": "test",
          "script": {
            "exec": [
              "pm.environment.set(\"token\", pm.response.json().access_token);\r",
              ""
            ],
            "type": "text/javascript",
            "packages": {},
            "requests": {}
          }
        }
      ],
      "request": {
        "method": "POST",
        "header": [],
        "body": {
          "mode": "raw",
          "raw": "{\r\n  \"username\": \"admin\",\r\n  \"password\": \"admin123\"\r\n}",
          "options": {
            "raw": {
              "language": "json"
            }
          }
        },
        "url": {
          "raw": "http://localhost:3000/auth/login",
          "protocol": "http",
          "host": [
            "localhost"
          ],
          "port": "3000",
          "path": [
            "auth",
            "login"
          ]
        }
      },
      "response": []
    },
    {
      "name": "Create Team",
      "request": {
        "method": "POST",
        "header": [
          {
            "key": "Authorization",
            "value": "Bearer {{token}}",
            "type": "text"
          },
          {
            "key": "Content-Type",
            "value": "application/json",
            "type": "text"
          }
        ],
        "body": {
          "mode": "raw",
          "raw": "{\r\n  \"name\": \"Backend Team\",\r\n  \"members\": [\r\n    { \"name\": \"Alice\", \"email\": \"alice@mail.com\" },\r\n    { \"name\": \"Bob\", \"email\": \"bob@mail.com\" }\r\n  ]\r\n}",
          "options": {
            "raw": {
              "language": "json"
            }
          }
        },
        "url": {
          "raw": "http://localhost:3000/team",
          "protocol": "http",
          "host": [
            "localhost"
          ],
          "port": "3000",
          "path": [
            "team"
          ]
        }
      },
      "response": []
    },
    {
      "name": "Create Task",
      "request": {
        "method": "POST",
        "header": [
          {
            "key": "Authorization",
            "value": "Bearer {{token}}",
            "type": "text"
          }
        ],
        "body": {
          "mode": "raw",
          "raw": "{\r\n  \"description\": \"Finish assignment\",\r\n  \"dueDate\": \"2026-02-10\"\r\n}\r\n",
          "options": {
            "raw": {
              "language": "json"
            }
          }
        },
        "url": {
          "raw": "http://localhost:3000/tasks",
          "protocol": "http",
          "host": [
            "localhost"
          ],
          "port": "3000",
          "path": [
            "tasks"
          ]
        }
      },
      "response": []
    },
    {
      "name": "Assign Task",
      "request": {
        "method": "PATCH",
        "header": [
          {
            "key": "Authorization",
            "value": "Bearer {{token}}",
            "type": "text"
          }
        ],
        "body": {
          "mode": "raw",
          "raw": "",
          "options": {
            "raw": {
              "language": "json"
            }
          }
        },
        "url": {
          "raw": "http://localhost:3000/tasks/1/assign/1",
          "protocol": "http",
          "host": [
            "localhost"
          ],
          "port": "3000",
          "path": [
            "tasks",
            "1",
            "assign",
            "1"
          ]
        }
      },
      "response": []
    },
    {
      "name": "Update Status",
      "request": {
        "method": "PATCH",
        "header": [
          {
            "key": "Authorization",
            "value": "Bearer {{token}}",
            "type": "text"
          }
        ],
        "body": {
          "mode": "raw",
          "raw": "{\r\n  \"status\": \"DONE\"\r\n}\r\n",
          "options": {
            "raw": {
              "language": "json"
            }
          }
        },
        "url": {
          "raw": "http://localhost:3000/tasks/1/status",
          "protocol": "http",
          "host": [
            "localhost"
          ],
          "port": "3000",
          "path": [
            "tasks",
            "1",
            "status"
          ]
        }
      },
      "response": []
    },
    {
      "name": "Get all tasks",
      "request": {
        "method": "GET",
        "header": [
          {
            "key": "Authorization",
            "value": "Bearer {{token}}",
            "type": "text"
          }
        ],
        "url": {
          "raw": "http://localhost:3000/tasks",
          "protocol": "http",
          "host": [
            "localhost"
          ],
          "port": "3000",
          "path": [
            "tasks"
          ]
        }
      },
      "response": []
    }
  ]
}